tei_validator.py
tei_validator-0.1.2.dist-info/LICENSE
tei_validator-0.1.2.dist-info/METADATA
tei_validator-0.1.2.dist-info/WHEEL
tei_validator-0.1.2.dist-info/entry_points.txt
tei_validator-0.1.2.dist-info/top_level.txt
tei_validator-0.1.2.dist-info/RECORD
