Metadata-Version: 2.1
Name: tei-validator
Version: 0.1.2
Summary: TEI XML validation package
Home-page: UNKNOWN
License: Apache License, Version 2.0
Platform: UNKNOWN
Classifier: Programming Language :: Python :: 3
Classifier: License :: OSI Approved :: MIT License
Classifier: Operating System :: OS Independent
Requires-Python: >=3.7
License-File: LICENSE
Requires-Dist: lxml (~=4.6)
Provides-Extra: dist
Requires-Dist: build (~=0.7) ; extra == 'dist'
Requires-Dist: twine (~=3.6) ; extra == 'dist'
Provides-Extra: test
Requires-Dist: pytest (~=6.2) ; extra == 'test'
